text_watermark/__init__.py
text_watermark/attack.py
text_watermark/extract.py
text_watermark/functions.py
text_watermark/pool.py
text_watermark/recover.py
text_watermark/shinywork.py
text_watermark/version.py
steganography_of_static_computing-0.2.5.dist-info/METADATA
steganography_of_static_computing-0.2.5.dist-info/WHEEL
steganography_of_static_computing-0.2.5.dist-info/top_level.txt
steganography_of_static_computing-0.2.5.dist-info/RECORD
