Metadata-Version: 2.1
Name: steganography-of-static-computing
Version: 0.2.5
Summary: project
Home-page: https://github.com/ECUsam/Steganography
Author: ECUsam
Author-email: wangyanzhao2003@gmail.com
License: UNKNOWN
Platform: UNKNOWN
Classifier: Programming Language :: Python :: 3
Classifier: License :: OSI Approved :: MIT License
Classifier: Operating System :: OS Independent
Requires-Python: >=3.6
Requires-Dist: shiny
Requires-Dist: opencv-python
Requires-Dist: numpy
Requires-Dist: line-profiler
Requires-Dist: Pillow
Requires-Dist: PyWavelets
